pubtools/_marketplacesvm/__init__.py
pubtools/_marketplacesvm/arguments.py
pubtools/_marketplacesvm/step.py
pubtools/_marketplacesvm/task.py
pubtools/_marketplacesvm/utils.py
pubtools/_marketplacesvm/cloud_providers/__init__.py
pubtools/_marketplacesvm/cloud_providers/aws.py
pubtools/_marketplacesvm/cloud_providers/base.py
pubtools/_marketplacesvm/cloud_providers/ms_azure.py
pubtools/_marketplacesvm/services/__init__.py
pubtools/_marketplacesvm/services/base.py
pubtools/_marketplacesvm/services/cloud.py
pubtools/_marketplacesvm/services/collector.py
pubtools/_marketplacesvm/services/rhsm.py
pubtools/_marketplacesvm/services/starmap.py
pubtools/_marketplacesvm/tasks/__init__.py
pubtools/_marketplacesvm/tasks/combined_push/__init__.py
pubtools/_marketplacesvm/tasks/combined_push/command.py
pubtools/_marketplacesvm/tasks/community_push/__init__.py
pubtools/_marketplacesvm/tasks/community_push/command.py
pubtools/_marketplacesvm/tasks/community_push/items.py
pubtools/_marketplacesvm/tasks/delete/__init__.py
pubtools/_marketplacesvm/tasks/delete/command.py
pubtools/_marketplacesvm/tasks/push/__init__.py
pubtools/_marketplacesvm/tasks/push/command.py
pubtools/_marketplacesvm/tasks/push/items/__init__.py
pubtools/_marketplacesvm/tasks/push/items/ami.py
pubtools/_marketplacesvm/tasks/push/items/starmap.py
pubtools/_marketplacesvm/tasks/push/items/state.py
pubtools_marketplacesvm-2.0.0.dist-info/LICENSE
pubtools_marketplacesvm-2.0.0.dist-info/METADATA
pubtools_marketplacesvm-2.0.0.dist-info/WHEEL
pubtools_marketplacesvm-2.0.0.dist-info/entry_points.txt
pubtools_marketplacesvm-2.0.0.dist-info/top_level.txt
pubtools_marketplacesvm-2.0.0.dist-info/RECORD
