Metadata-Version: 2.1
Name: pubtools-marketplacesvm
Version: 2.0.0
Summary: Publishing tools for various Cloud Marketplaces
Home-page: https://github.com/release-engineering/pubtools-marketplacesvm
License: GPLv3+
Classifier: Development Status :: 4 - Beta
Classifier: Intended Audience :: Developers
Classifier: License :: OSI Approved :: GNU General Public License v3 or later (GPLv3+)
Classifier: Programming Language :: Python :: 3.10
Classifier: Programming Language :: Python :: 3.11
Classifier: Programming Language :: Python :: 3.12
Classifier: Programming Language :: Python :: 3.13
Classifier: Topic :: Software Development :: Libraries :: Python Modules
License-File: LICENSE
Requires-Dist: cloudimg>=1.15.0
Requires-Dist: pubtools>=1.4.3
Requires-Dist: more-executors>=2.11.4
Requires-Dist: pushcollector>=1.3.0
Requires-Dist: pushsource>=2.51.2
Requires-Dist: strenum>=0.4.15
Requires-Dist: starmap-client>=2.4.0
Requires-Dist: cloudpub>=1.6.0
